filter/__init__.py
filter/data.py
gui/__init__.py
gui/app.py
gui/pyqt5backend/__init__.py
gui/pyqt5backend/guidesign.py
gui/pyqt5backend/mplwidget_nav.py
segtool/__init__.py
segtool/main.py
flower_sementation_tool-0.1.2.dist-info/LICENSE
flower_sementation_tool-0.1.2.dist-info/METADATA
flower_sementation_tool-0.1.2.dist-info/WHEEL
flower_sementation_tool-0.1.2.dist-info/top_level.txt
flower_sementation_tool-0.1.2.dist-info/RECORD
